firebrick/__init__.py
firebrick/apps.py
firebrick/api/__init__.py
firebrick/api/argparser.py
firebrick/api/endpoint.py
firebrick/api/serializer.py
firebrick/database/__init__.py
firebrick/database/get_or_404.py
firebrick/exceptions/__init__.py
firebrick/exceptions/api.py
firebrick/management/__init__.py
firebrick/management/commands/__init__.py
firebrick/management/commands/startaccountsapp.py
firebrick/management/commands/startapi.py
firebrick/settings/__init__.py
firebrick/settings/account.py
firebrick/templates/__init__.py
firebrick/templates/templating.py
firebrick/templates/accounts/__init__.py
firebrick/templates/accounts/admin.py
firebrick/templates/accounts/apps.py
firebrick/templates/accounts/forms.py
firebrick/templates/accounts/models.py
firebrick/templates/accounts/signals.py
firebrick/templates/accounts/tests.py
firebrick/templates/accounts/views.py
firebrick/templates/accounts/migrations/__init__.py
firebrick/templates/accounts_templates/login.html
firebrick/templates/accounts_templates/logout.html
firebrick/templates/accounts_templates/register.html
firebrick/templates/api/__init__.py
firebrick/templates/api/admin.py
firebrick/templates/api/apps.py
firebrick/templates/api/models.py
firebrick/templates/api/tests.py
firebrick/templates/api/urls.py
firebrick/templates/api/views.py
firebrick/tests/__init__.py
firebrick/tests/asserts.py
firebrick/tests/test.py
Firebrick-2.0.0.dist-info/LICENSE
Firebrick-2.0.0.dist-info/METADATA
Firebrick-2.0.0.dist-info/WHEEL
Firebrick-2.0.0.dist-info/top_level.txt
Firebrick-2.0.0.dist-info/RECORD
