Metadata-Version: 2.1
Name: Firebrick
Version: 2.0.0
Summary: Django utilitys
Author: Logtism
License: UNKNOWN
Project-URL: Documentation, https://github.com/Logtism/Firebrick/wiki
Project-URL: Source, https://github.com/Logtism/Firebrick
Platform: UNKNOWN
Classifier: Environment :: Web Environment
Classifier: Framework :: Django
Classifier: Intended Audience :: Developers
Classifier: Programming Language :: Python :: 3
Classifier: Programming Language :: Python :: 3 :: Only
Classifier: Programming Language :: Python :: 3.9
Classifier: Programming Language :: Python :: 3.10
Classifier: License :: OSI Approved :: GNU General Public License v3 (GPLv3)
Requires-Python: >=3.9
License-File: LICENSE
Requires-Dist: django
Requires-Dist: django-crispy-forms
